{
    "directory" : "${archUpstreamSite}/core/os/${arch}",

    "packages" : {
        "bash" : {},
        "bzip2" : {},
        "coreutils" : {},
        "cryptsetup" : {},
        "device-mapper" : {},
        "dhcpcd" : {},
        "diffutils" : {},
        "e2fsprogs" : {},
        "file" : {},
        "filesystem" : {},
        "findutils" : {},
        "gawk" : {},
        "gcc-libs" : {},
        "gettext" : {},
        "glibc" : {},
        "grep" : {},
        "gzip" : {},
        "inetutils" : {},
        "iproute2" : {},
        "iputils" : {},
        "jfsutils" : {},
        "less" : {},
        "libutil-linux" : {},
        "licenses" : {},
        "linux" : {},
        "logrotate" : {},
        "lvm2" : {},
        "man-db" : {},
        "man-pages" : {},
        "mdadm" : {},
        "nano" : {},
        "netctl" : {},
        "openssh" : {},
        "pacman" : {},
        "pciutils" : {},
        "pcmciautils" : {},
        "perl" : {},
        "procps-ng" : {},
        "psmisc" : {},
        "reiserfsprogs" : {},
        "s-nail" : {},
        "sed" : {},
        "shadow" : {},
        "sudo" : {},
        "sysfsutils" : {},
        "systemd-sysvcompat" : {},
        "tar" : {},
        "texinfo" : {},
        "usbutils" : {},
        "util-linux" : {},
        "vi" : {},
        "which" : {},
        "xfsprogs" : {},

# Dependencies of base packages, recursive
        "acl" : {},
        "archlinux-keyring" : {},
        "attr" : {},
        "bash" : {},
        "ca-certificates" : {},
        "coreutils" : {},
        "cracklib" : {},
        "cronie" : {},
        "cryptsetup" : {},
        "curl" : {},
        "db" : {},
        "dbus" : {},
        "device-mapper" : {},
        "dirmngr" : {},
        "expat" : {},
        "filesystem" : {},
        "findutils" : {},
        "gcc-libs" : {},
        "gdbm" : {},
        "glib2" : {},
        "gmp" : {},
        "gnupg" : {},
        "gpgme" : {},
        "groff" : {},
        "gzip" : {},
        "hwids" : {},
        "iana-etc" : {},
        "inetutils" : {},
        "iproute2" : {},
        "iptables" : {},
        "jfsutils" : {},
        "kbd" : {},
        "keyutils" : {},
        "kmod" : {},
        "krb5" : {},
        "less" : {},
        "libarchive" : {},
        "libassuan" : {},
        "libcap" : {},
        "libdbus" : {},
        "libedit" : {},
        "libffi" : {},
        "libgcrypt" : {},
        "libgpg-error" : {},
        "libksba" : {},
        "libldap" : {},
        "libpipeline" : {},
        "libsasl" : {},
        "libseccomp" : {},
        "libssh2" : {},
        "libsystemd" : {},
        "libtirpc" : {},
        "libusb" : {},
        "linux" : {},
        "linux-api-headers" : {},
        "linux-firmware" : {},
        "lvm2" : {},
        "lzo2" : {},
        "mkinitcpio" : {},
        "mkinitcpio-busybox" : {},
        "mpfr" : {},
        "netctl" : {},
        "ncurses" : {},
        "openresolv" : {},
        "openssl" : {},
        "pacman" : {},
        "pacman-mirrorlist" : {},
        "pam" : {},
        "pambase" : {},
        "pcmciautils" : {},
        "pcre" : {},
        "perl" : {},
        "pinentry" : {},
        "popt" : {},
        "procps-ng" : {},
        "pth" : {},
        "readline" : {},
        "reiserfsprogs" : {},
        "run-parts" : {},
        "shadow" : {},
        "sysfsutils" : {},
        "systemd" : {},
        "systemd-sysvcompat" : {},
        "tzdata" : {},
        "usbutils" : {},
        "util-linux" : {},
        "xfsprogs" : {},
        "xz" : {},
        "zlib" : {},

# Boot loader
        "grub" : {},

# btrfs support
        "btrfs-progs" : {}
    }
}
